seekgpt/__init__.py
seekgpt/client.py
seekgpt-0.1.3.dist-info/licenses/LICENSE
seekgpt-0.1.3.dist-info/METADATA
seekgpt-0.1.3.dist-info/WHEEL
seekgpt-0.1.3.dist-info/top_level.txt
seekgpt-0.1.3.dist-info/RECORD
