Metadata-Version: 2.4
Name: seekgpt
Version: 0.1.3
Summary: A Python client library for SeekGPT and other OpenAI-compatible LLM APIs.
Author-email: SeekGPT Team / Sanjib Narzary <seekgpt.org@gmail.com>
License: MIT
Project-URL: Homepage, https://github.com/seekgpt/seekgpt-python
Project-URL: Repository, https://github.com/seekgpt/seekgpt-python
Project-URL: Bug Tracker, https://github.com/seekgpt/seekgpt-python/issues
Keywords: llm,ai,openai,seekgpt,gemini,anthropic,cohere,ollama,vllm,api,client,chatgpt,generative ai,nlp
Classifier: Development Status :: 3 - Alpha
Classifier: Programming Language :: Python :: 3
Classifier: Programming Language :: Python :: 3.8
Classifier: Programming Language :: Python :: 3.9
Classifier: Programming Language :: Python :: 3.10
Classifier: Programming Language :: Python :: 3.11
Classifier: Programming Language :: Python :: 3.12
Classifier: License :: OSI Approved :: MIT License
Classifier: Operating System :: OS Independent
Classifier: Intended Audience :: Developers
Classifier: Topic :: Scientific/Engineering :: Artificial Intelligence
Classifier: Topic :: Software Development :: Libraries :: Python Modules
Classifier: Topic :: Communications :: Chat
Classifier: Typing :: Typed
Requires-Python: >=3.8
License-File: LICENSE
Requires-Dist: requests>=2.26.0
Requires-Dist: dotenv>=0.9.9
Dynamic: license-file
